ocrd_browser/__init__.py
ocrd_browser/application.py
ocrd_browser/main.py
ocrd_browser/ui.gresource
ocrd_browser/model/__init__.py
ocrd_browser/model/document.py
ocrd_browser/model/page.py
ocrd_browser/model/page_xml_renderer.py
ocrd_browser/resources/__init__.py
ocrd_browser/resources/about-dialog.ui
ocrd_browser/resources/main-window.ui
ocrd_browser/resources/open-dialog.ui
ocrd_browser/resources/page-list.ui
ocrd_browser/resources/save-dialog.ui
ocrd_browser/ui/__init__.py
ocrd_browser/ui/dialogs.py
ocrd_browser/ui/icon_store.py
ocrd_browser/ui/page_browser.py
ocrd_browser/ui/page_store.py
ocrd_browser/ui/window.py
ocrd_browser/util/__init__.py
ocrd_browser/util/config.py
ocrd_browser/util/file_groups.py
ocrd_browser/util/gtk.py
ocrd_browser/util/image.py
ocrd_browser/util/launcher.py
ocrd_browser/util/streams.py
ocrd_browser/view/__init__.py
ocrd_browser/view/base.py
ocrd_browser/view/diff.py
ocrd_browser/view/empty.py
ocrd_browser/view/html.py
ocrd_browser/view/images.py
ocrd_browser/view/manager.py
ocrd_browser/view/page.py
ocrd_browser/view/registry.py
ocrd_browser/view/text.py
ocrd_browser/view/xml.py
browse_ocrd-0.5.5.dist-info/LICENSE
browse_ocrd-0.5.5.dist-info/METADATA
browse_ocrd-0.5.5.dist-info/WHEEL
browse_ocrd-0.5.5.dist-info/entry_points.txt
browse_ocrd-0.5.5.dist-info/top_level.txt
browse_ocrd-0.5.5.dist-info/RECORD
