Metadata-Version: 2.1
Name: browse-ocrd
Version: 0.5.5
Summary: An extensible viewer for OCR-D workspaces
Home-page: https://github.com/hnesk/browse-ocrd
Author: Johannes Künsebeck
Author-email: kuensebeck@googlemail.com
License: MIT License
Keywords: OCR,OCR-D,mets,PAGE Xml
Classifier: Programming Language :: Python :: 3
Classifier: Programming Language :: Python :: 3
Classifier: Programming Language :: Python :: 3 :: Only
Classifier: Programming Language :: Python :: 3.7
Classifier: Programming Language :: Python :: 3.8
Classifier: Programming Language :: Python :: 3.9
Classifier: License :: OSI Approved :: MIT License
Classifier: Development Status :: 5 - Production/Stable
Classifier: Environment :: X11 Applications :: GTK
Classifier: Intended Audience :: Developers
Classifier: Intended Audience :: End Users/Desktop
Classifier: Intended Audience :: Science/Research
Classifier: Topic :: Scientific/Engineering :: Image Recognition
Requires-Python: >=3.7
License-File: LICENSE
Requires-Dist: ocrd (>=2.43.0)
Requires-Dist: Pillow
Requires-Dist: numpy (>=1.20)
Requires-Dist: opencv-python-headless
Requires-Dist: PyGObject (>=3.28)
Requires-Dist: python-magic
Requires-Dist: wheel
Requires-Dist: setuptools
Requires-Dist: lxml
Requires-Dist: Shapely
Requires-Dist: Deprecated
Requires-Dist: importlib-metadata (>=3.6)
Requires-Dist: pydantic (~=1.10)
Requires-Dist: importlib-resources ; python_version < "3.8"
